pineflow/monitors/watsonx/__init__.py
pineflow/monitors/watsonx/base.py
pineflow_monitors_watsonx-0.7.7.dist-info/METADATA
pineflow_monitors_watsonx-0.7.7.dist-info/WHEEL
pineflow_monitors_watsonx-0.7.7.dist-info/RECORD
