Metadata-Version: 2.4
Name: pineflow-monitors-watsonx
Version: 0.7.7
Summary: pineflow monitors watsonx extension
Author-email: Leonardo Furnielis <leonardofurnielis@outlook.com>
License: MIT
Requires-Python: <4.0,>=3.10
Requires-Dist: certifi<2026.0.0,>=2025.4.26
Requires-Dist: ibm-aigov-facts-client<1.1.0,>=1.0.95
Requires-Dist: ibm-watson-openscale<3.1.0,>=3.0.47
Requires-Dist: ibm-watsonx-ai<2.0.0,>=1.3.26
Requires-Dist: ipython==8.37.0
Requires-Dist: pineflow-core<0.8.0,>=0.7.8
Provides-Extra: dev
Requires-Dist: ruff>=0.11.13; extra == 'dev'
